rustshogi-0.8.0.dist-info/METADATA
rustshogi-0.8.0.dist-info/WHEEL
rustshogi-0.8.0.dist-info/licenses/LICENSE
rustshogi/__init__.py
rustshogi/rustshogi.cpython-38-s390x-linux-gnu.so
rustshogi-0.8.0.dist-info/RECORD
